finetune_embedder/main.py
finetune_embedder/py.typed
finetune_embedder/src/__init__.py
finetune_embedder/src/constants.py
finetune_embedder/src/exceptions.py
finetune_embedder/src/mixins.py
finetune_embedder/src/push_to_hf/__init__.py
finetune_embedder/src/push_to_hf/main.py
finetune_embedder/src/settings.py
finetune_embedder/src/train/__init__.py
finetune_embedder/src/train/datasets/__init__.py
finetune_embedder/src/train/datasets/collate.py
finetune_embedder/src/train/datasets/dataset.py
finetune_embedder/src/train/datasets/sampling/__init__.py
finetune_embedder/src/train/datasets/sampling/samplers.py
finetune_embedder/src/train/datasets/token_counter.py
finetune_embedder/src/train/models/__init__.py
finetune_embedder/src/train/models/graph_embedder.py
finetune_embedder/src/train/models/graph_embedder_hf/__init__.py
finetune_embedder/src/train/models/graph_embedder_hf/configuration_graph_embedder.py
finetune_embedder/src/train/models/graph_embedder_hf/modeling_graph_embedder.py
finetune_embedder/src/train/preprocess/__init__.py
finetune_embedder/src/train/preprocess/preprocess.py
finetune_embedder/src/train/runners/__init__.py
finetune_embedder/src/train/runners/runner.py
finetune_embedder/src/train/trainers/__init__.py
finetune_embedder/src/train/trainers/loss.py
finetune_embedder/src/train/trainers/trainer.py
finetune_embedder/src/utils.py
finetune_embedder-0.1.0.dist-info/METADATA
finetune_embedder-0.1.0.dist-info/WHEEL
finetune_embedder-0.1.0.dist-info/RECORD
