Metadata-Version: 2.4
Name: finetune-embedder
Version: 0.1.0
Summary: 
Author: jalal
Author-email: jalalkhaldi3@gmail.com
Requires-Python: =3.12.9
Classifier: Programming Language :: Python :: 3
Requires-Dist: einops (>=0.8.1,<0.9.0)
Requires-Dist: huggingface-hub[cli] (>=0.34.0,<1.0.0)
Requires-Dist: langchain-huggingface (>=1.1.0,<2.0.0)
Requires-Dist: minio (>=7.2.20,<8.0.0)
Requires-Dist: mypy (>=1.19.0,<2.0.0)
Requires-Dist: neo4j (>=6.0.3,<7.0.0)
Requires-Dist: numpy (>=1.24,<2.3)
Requires-Dist: pandas (>=2.3.3,<3.0.0)
Requires-Dist: polars (>=1.36.0,<2.0.0)
Requires-Dist: pre-commit (>=4.5.0,<5.0.0)
Requires-Dist: pyarrow (>=22.0.0,<23.0.0)
Requires-Dist: pydantic-settings (>=2.12.0,<3.0.0)
Requires-Dist: sentence-transformers (>=5.1.2,<6.0.0)
Requires-Dist: tensorboard (>=2.20.0,<3.0.0)
Requires-Dist: torch (>=2.9.0,<3.0.0)
Requires-Dist: transformers (>=4.57.3,<5.0.0)
Requires-Dist: types-tqdm (>=4.67.0.20250809,<5.0.0.0)
Requires-Dist: vllm (>=0.12.0,<0.13.0)
